mlserver_huggingface/__init__.py
mlserver_huggingface/codecs/__init__.py
mlserver_huggingface/codecs/base.py
mlserver_huggingface/codecs/conversation.py
mlserver_huggingface/codecs/image.py
mlserver_huggingface/codecs/json.py
mlserver_huggingface/codecs/jsonlist.py
mlserver_huggingface/codecs/numpylist.py
mlserver_huggingface/codecs/raw.py
mlserver_huggingface/codecs/utils.py
mlserver_huggingface/common.py
mlserver_huggingface/errors.py
mlserver_huggingface/metadata.py
mlserver_huggingface/runtime.py
mlserver_huggingface/settings.py
mlserver_huggingface/version.py
mlserver_huggingface-1.7.1.dist-info/LICENSE
mlserver_huggingface-1.7.1.dist-info/METADATA
mlserver_huggingface-1.7.1.dist-info/WHEEL
mlserver_huggingface-1.7.1.dist-info/RECORD
