Metadata-Version: 2.3
Name: mlserver-huggingface
Version: 1.7.1
Summary: HuggingFace runtime for MLServer
License: Apache-2.0
Author: Seldon Technologies Ltd.
Author-email: hello@seldon.io
Requires-Python: >=3.9,<3.13
Classifier: License :: OSI Approved :: Apache Software License
Classifier: Programming Language :: Python :: 3
Classifier: Programming Language :: Python :: 3.9
Classifier: Programming Language :: Python :: 3.10
Classifier: Programming Language :: Python :: 3.11
Classifier: Programming Language :: Python :: 3.12
Requires-Dist: mlserver
Requires-Dist: onnxruntime (<1.20.0) ; python_version < "3.10"
Requires-Dist: onnxruntime ; python_version >= "3.10"
Requires-Dist: optimum[onnxruntime] (>=1.4,<2.0)
Requires-Dist: pillow
Requires-Dist: tensorflow
Requires-Dist: tf-keras (>=2.16.0)
Requires-Dist: torch
